brainviewer/__init__.py
brainviewer/__main__.py
brainviewer/fig/brain.ico
brainviewer/fig/LOGO.jpg
brainviewer/fig/main_window.png
brainviewer/gui/splash.py
brainviewer/gui/viewer.py
brainviewer/gui/viewer.ui
brainviewer/gui/viewer_ui.py
brainviewer/runtime/main.spec
brainviewer/utils/brain.py
brainviewer/utils/config.py
brainviewer/utils/freesurfer.py
brainviewer/utils/FreeSurferColorLUT.txt
brainviewer/utils/numeric.py
brainviewer/utils/surface.py
brainviewer/utils/VepFreeSurferColorLut.txt
brainviewer-0.1.2.dist-info/LICENSE
brainviewer-0.1.2.dist-info/METADATA
brainviewer-0.1.2.dist-info/WHEEL
brainviewer-0.1.2.dist-info/RECORD
